genepy.py
genepy_cli-0.6.dist-info/METADATA
genepy_cli-0.6.dist-info/WHEEL
genepy_cli-0.6.dist-info/entry_points.txt
genepy_cli-0.6.dist-info/top_level.txt
genepy_cli-0.6.dist-info/RECORD
