Metadata-Version: 2.4
Name: genepy-cli
Version: 0.6
Summary: Genepy client.
Author-email: Julien Palard <julien@palard.fr>
License-Expression: MIT
Project-URL: Homepage, https://git.afpy.org/mdk/genepy-cli/
Requires-Python: >=3.8
Requires-Dist: rich
Requires-Dist: requests
Requires-Dist: websocket-client
Requires-Dist: python-slugify
